reahl/browsertools/__init__.py
reahl/browsertools/browsertools.py
reahl/browsertools_dev/__init__.py
reahl_browsertools-7.0.3.dist-info/LICENSE
reahl_browsertools-7.0.3.dist-info/METADATA
reahl_browsertools-7.0.3.dist-info/WHEEL
reahl_browsertools-7.0.3.dist-info/reahl-component.toml
reahl_browsertools-7.0.3.dist-info/top_level.txt
reahl_browsertools-7.0.3.dist-info/RECORD
