Metadata-Version: 2.1
Name: reahl-browsertools
Version: 7.0.3
Summary: An alternative API for working with Selenium and WebTest.
Author-email: Iwan Vosloo <iwan@reahl.org>, Craig Sparks <craig@reahl.org>
Classifier: Development Status :: 5 - Production/Stable
Classifier: Intended Audience :: Developers
Classifier: License :: OSI Approved
Classifier: Operating System :: OS Independent
Classifier: Programming Language :: Python :: 3
Classifier: Topic :: Software Development :: Testing
Classifier: Environment :: Web Environment
Requires-Python: >=3.8
License-File: LICENSE
Requires-Dist: lxml <5.1.999,>=4.2
Requires-Dist: WebTest <3.0.999,>=2.0
Requires-Dist: selenium <4.17.9999,>=2.42
